nicole/__init__.py
nicole/blocks.py
nicole/contract.py
nicole/decomp.py
nicole/display.py
nicole/identity.py
nicole/index.py
nicole/operators.py
nicole/space.py
nicole/tensor.py
nicole/typing.py
nicole/symmetry/__init__.py
nicole/symmetry/abelian.py
nicole/symmetry/base.py
nicole/symmetry/product.py
nicole-0.1.0.dist-info/METADATA
nicole-0.1.0.dist-info/WHEEL
nicole-0.1.0.dist-info/licenses/LICENSE
nicole-0.1.0.dist-info/RECORD
