Metadata-Version: 2.4
Name: nicole
Version: 0.1.0
Summary: Nicole: a symmetry-aware tensor library
Project-URL: Homepage, https://github.com/Ideogenesis-AI/Nicole
Project-URL: Documentation, https://ideogenesis-ai.github.io/Nicole
Project-URL: Repository, https://github.com/Ideogenesis-AI/Nicole
Project-URL: Issues, https://github.com/Ideogenesis-AI/Nicole/issues
Author-email: Changkai Zhang <changkai.zhang@lmu.de>
License:                     GNU GENERAL PUBLIC LICENSE
License-File: LICENSE
Keywords: abelian,block-symmetric,numpy,quantum,symmetry,tensor
Classifier: Development Status :: 3 - Alpha
Classifier: Intended Audience :: Science/Research
Classifier: License :: OSI Approved :: GNU General Public License v3 (GPLv3)
Classifier: Programming Language :: Python :: 3
Classifier: Programming Language :: Python :: 3.11
Classifier: Programming Language :: Python :: 3.12
Classifier: Topic :: Scientific/Engineering :: Physics
Requires-Python: >=3.11
Requires-Dist: numpy>=2.0
Provides-Extra: docs
Requires-Dist: mkdocs-material-extensions>=1.3; extra == 'docs'
Requires-Dist: mkdocs-material>=9.5; extra == 'docs'
Requires-Dist: mkdocs>=1.5; extra == 'docs'
Requires-Dist: mkdocstrings[python]>=0.24; extra == 'docs'
Provides-Extra: lint
Requires-Dist: mypy>=1.8; extra == 'lint'
Requires-Dist: ruff>=0.6; extra == 'lint'
Provides-Extra: test
Requires-Dist: hypothesis>=6.0; extra == 'test'
Requires-Dist: pytest-benchmark>=4.0; extra == 'test'
Requires-Dist: pytest>=7.0; extra == 'test'
